thsauto/__init__.py
thsauto/__main__.py
thsauto/_version.py
thsauto/app.py
thsauto/base.py
thsauto/cli.py
thsauto/parse.py
thsauto/ths.py
thsauto/utils.py
thsauto/xpath.py
thsauto-0.3.4.dist-info/LICENSE
thsauto-0.3.4.dist-info/METADATA
thsauto-0.3.4.dist-info/WHEEL
thsauto-0.3.4.dist-info/entry_points.txt
thsauto-0.3.4.dist-info/top_level.txt
thsauto-0.3.4.dist-info/RECORD
