Metadata-Version: 2.1
Name: thsauto
Version: 0.3.4
Summary: ths automation test
Author-email: wukan <wu-kan@163.com>
License: MIT
Keywords: ths,automation
Classifier: Development Status :: 4 - Beta
Classifier: Programming Language :: Python
Requires-Python: >=3.8
License-File: LICENSE
Requires-Dist: pandas
Requires-Dist: uiautomator2
Requires-Dist: lxml
Requires-Dist: loguru
Provides-Extra: cli
Requires-Dist: fastapi ; extra == 'cli'
Requires-Dist: uvicorn[standard] ; extra == 'cli'
Requires-Dist: fire ; extra == 'cli'
Requires-Dist: requests ; extra == 'cli'
